{
	"ASASSN-18yf":{
		"schema":"https://github.com/astrocatalogs/supernovae/blob/d3ef5fc/SCHEMA.md",
		"name":"ASASSN-18yf",
		"sources":[
			{
				"name":"2016A&A...594A..13P",
				"bibcode":"2016A&A...594A..13P",
				"reference":"Planck Collaboration et al. (2016)",
				"alias":"1"
			},
			{
				"name":"Transient Name Server",
				"url":"https://wis-tns.weizmann.ac.il/",
				"alias":"2"
			},
			{
				"name":"Latest Supernovae",
				"secondary":true,
				"url":"http://www.rochesterastronomy.org/snimages/snredshiftall.html",
				"alias":"3"
			},
			{
				"name":"The Open Supernova Catalog",
				"bibcode":"2017ApJ...835...64G",
				"reference":"Guillochon et al. (2017)",
				"secondary":true,
				"url":"https://sne.space",
				"alias":"4"
			}
		],
		"alias":[
			{
				"value":"ASASSN-18yf",
				"source":"2,3"
			},
			{
				"value":"AT2018hme",
				"source":"2,3"
			}
		],
		"comovingdist":[
			{
				"value":"62.298",
				"derived":true,
				"u_value":"Mpc",
				"source":"1,2,4"
			}
		],
		"dec":[
			{
				"value":"-17:23:10.90",
				"u_value":"degrees",
				"source":"2,3"
			}
		],
		"discoverdate":[
			{
				"value":"2018/10/20.37",
				"source":"2"
			}
		],
		"discoverer":[
			{
				"value":"ASAS-SN",
				"source":"2,3"
			}
		],
		"host":[
			{
				"value":"MCG -03-25-010",
				"source":"2"
			},
			{
				"value":"MCG -03-25-10",
				"source":"2,3"
			}
		],
		"hostcomovingdist":[
			{
				"value":"62.298",
				"derived":true,
				"source":"1,2,4"
			}
		],
		"hostlumdist":[
			{
				"value":"63.1779",
				"derived":true,
				"source":"1,2,4"
			}
		],
		"hostredshift":[
			{
				"value":"0.014123",
				"source":"2"
			}
		],
		"hostvelocity":[
			{
				"value":"4204.1",
				"source":"4"
			}
		],
		"lumdist":[
			{
				"value":"63.1779",
				"derived":true,
				"u_value":"Mpc",
				"source":"1,2,4"
			}
		],
		"maxabsmag":[
			{
				"value":"-18.1876",
				"derived":true,
				"source":"1,2,4"
			}
		],
		"maxappmag":[
			{
				"value":"15.8",
				"derived":true,
				"source":"2,4"
			}
		],
		"maxband":[
			{
				"value":"g",
				"derived":true,
				"source":"2,4"
			}
		],
		"maxdate":[
			{
				"value":"2018/10/20",
				"derived":true,
				"source":"2,4"
			}
		],
		"maxvisualabsmag":[
			{
				"value":"-18.2028",
				"derived":true,
				"source":"1,2,4"
			}
		],
		"maxvisualappmag":[
			{
				"value":"15.8",
				"derived":true,
				"source":"2,4"
			}
		],
		"maxvisualband":[
			{
				"value":"g",
				"derived":true,
				"source":"2,4"
			}
		],
		"maxvisualdate":[
			{
				"value":"2018/10/20",
				"derived":true,
				"source":"2,4"
			}
		],
		"ra":[
			{
				"value":"09:35:39.43",
				"u_value":"hours",
				"source":"2"
			},
			{
				"value":"09:35:39.430",
				"u_value":"hours",
				"source":"2,3"
			}
		],
		"redshift":[
			{
				"value":"0.014123",
				"kind":"host",
				"source":"2"
			},
			{
				"value":"0.014123",
				"source":"2,3"
			}
		],
		"velocity":[
			{
				"value":"4204.1",
				"u_value":"km/s",
				"source":"4"
			}
		],
		"photometry":[
			{
				"time":"58401.11",
				"band":"g",
				"instrument":"Payne-Gaposchkin",
				"magnitude":"17.5",
				"telescope":"ASASSN-5",
				"u_time":"MJD",
				"upperlimit":true,
				"source":"2"
			},
			{
				"time":"58411.37",
				"band":"g",
				"instrument":"Paczynski",
				"magnitude":"15.8",
				"telescope":"ASASSN-3",
				"u_time":"MJD",
				"source":"2"
			}
		]
	}
}