{
	"AT2017fmw":{
		"schema":"https://github.com/astrocatalogs/supernovae/blob/5d080fc/SCHEMA.md",
		"name":"AT2017fmw",
		"sources":[
			{
				"name":"2016A&A...594A..13P",
				"bibcode":"2016A&A...594A..13P",
				"reference":"Planck Collaboration et al. (2016)",
				"alias":"1"
			},
			{
				"name":"2011ApJ...737..103S",
				"bibcode":"2011ApJ...737..103S",
				"reference":"Schlafly & Finkbeiner (2011)",
				"alias":"2"
			},
			{
				"name":"Transient Name Server",
				"url":"https://wis-tns.weizmann.ac.il/",
				"alias":"3"
			},
			{
				"name":"Gaia Photometric Science Alerts",
				"url":"http://gsaweb.ast.cam.ac.uk/alerts/alertsindex",
				"alias":"4"
			},
			{
				"name":"Latest Supernovae",
				"secondary":true,
				"url":"http://www.rochesterastronomy.org/snimages/snredshiftall.html",
				"alias":"5"
			},
			{
				"name":"The Open Supernova Catalog",
				"bibcode":"2017ApJ...835...64G",
				"reference":"Guillochon et al. (2017)",
				"secondary":true,
				"url":"https://sne.space",
				"alias":"6"
			}
		],
		"alias":[
			{
				"value":"AT2017fmw",
				"source":"3,4,5"
			},
			{
				"value":"ATLAS17ipg",
				"source":"3,5"
			},
			{
				"value":"Gaia17bwx",
				"source":"3,5"
			}
		],
		"claimedtype":[
			{
				"value":"Candidate",
				"source":"4"
			}
		],
		"comovingdist":[
			{
				"value":"104.93",
				"derived":true,
				"u_value":"Mpc",
				"source":"1,3,5,6"
			}
		],
		"dec":[
			{
				"value":"+06:18:16.75",
				"u_value":"degrees",
				"source":"3,5"
			},
			{
				"value":"+06:18:16.812",
				"u_value":"degrees",
				"source":"4"
			}
		],
		"discoverdate":[
			{
				"value":"2017/07/11.332998",
				"source":"3"
			}
		],
		"discoverer":[
			{
				"value":"ATLAS",
				"source":"3,5"
			}
		],
		"ebv":[
			{
				"value":"0.0336",
				"derived":true,
				"e_value":"0.0006",
				"source":"2,6"
			}
		],
		"host":[
			{
				"value":"UGC 9454",
				"source":"3,5"
			}
		],
		"lumdist":[
			{
				"value":"107.437",
				"derived":true,
				"u_value":"Mpc",
				"source":"1,3,5,6"
			}
		],
		"maxabsmag":[
			{
				"value":"-17.3402",
				"derived":true,
				"source":"1,3,5,6"
			}
		],
		"maxappmag":[
			{
				"value":"17.79",
				"derived":true,
				"source":"4,6"
			}
		],
		"maxband":[
			{
				"value":"G",
				"derived":true,
				"source":"4,6"
			}
		],
		"maxdate":[
			{
				"value":"2017/07/27",
				"derived":true,
				"source":"4,6"
			}
		],
		"maxvisualabsmag":[
			{
				"value":"-17.3658",
				"derived":true,
				"source":"1,3,5,6"
			}
		],
		"maxvisualappmag":[
			{
				"value":"17.79",
				"derived":true,
				"source":"4,6"
			}
		],
		"maxvisualband":[
			{
				"value":"G",
				"derived":true,
				"source":"4,6"
			}
		],
		"maxvisualdate":[
			{
				"value":"2017/07/27",
				"derived":true,
				"source":"4,6"
			}
		],
		"ra":[
			{
				"value":"14:40:23.55",
				"u_value":"hours",
				"source":"3"
			},
			{
				"value":"14:40:23.550",
				"u_value":"hours",
				"source":"3,5"
			},
			{
				"value":"14:40:23.52",
				"u_value":"hours",
				"source":"4"
			}
		],
		"redshift":[
			{
				"value":"0.023843",
				"source":"3,5"
			}
		],
		"velocity":[
			{
				"value":"7062.8",
				"u_value":"km/s",
				"source":"6"
			}
		],
		"photometry":[
			{
				"time":"57921.8929977",
				"band":"G",
				"instrument":"Astrometric",
				"magnitude":"21.5",
				"observer":"Robot",
				"telescope":"Gaia",
				"u_time":"MJD",
				"upperlimit":true,
				"source":"3"
			},
			{
				"time":"57943.3629977",
				"band":"orange",
				"instrument":"ACAM1",
				"magnitude":"17.51",
				"observer":"Robot",
				"telescope":"ATLAS1",
				"u_time":"MJD",
				"upperlimit":true,
				"source":"3"
			},
			{
				"time":"57945.3329977",
				"band":"orange",
				"e_magnitude":"0.17",
				"instrument":"ACAM1",
				"magnitude":"18.62",
				"observer":"Robot",
				"telescope":"ATLAS1",
				"u_time":"MJD",
				"source":"3"
			},
			{
				"time":"57961.8579977",
				"band":"G",
				"e_magnitude":"0.2",
				"instrument":"Astrometric",
				"magnitude":"17.79",
				"observer":"Robot",
				"telescope":"Gaia",
				"u_time":"MJD",
				"source":"3"
			},
			{
				"time":"57961.859",
				"band":"G",
				"e_magnitude":"0.0",
				"instrument":"Astrometric",
				"magnitude":"17.79",
				"telescope":"GAIA",
				"u_time":"MJD",
				"source":"4"
			},
			{
				"time":"57961.933",
				"band":"G",
				"e_magnitude":"0.0",
				"instrument":"Astrometric",
				"magnitude":"17.82",
				"telescope":"GAIA",
				"u_time":"MJD",
				"source":"4"
			}
		]
	}
}