{
	"CSS170516:121702+400911":{
		"schema":"https://github.com/astrocatalogs/supernovae/blob/d3ef5fc/SCHEMA.md",
		"name":"CSS170516:121702+400911",
		"sources":[
			{
				"name":"2011ApJ...737..103S",
				"bibcode":"2011ApJ...737..103S",
				"reference":"Schlafly & Finkbeiner (2011)",
				"alias":"1"
			},
			{
				"name":"Catalina Sky Survey",
				"bibcode":"2009ApJ...696..870D",
				"reference":"Drake et al. (2009)",
				"url":"http://nesssi.cacr.caltech.edu/catalina/AllSN.html",
				"alias":"2"
			},
			{
				"name":"CRTS SN page",
				"url":"http://nesssi.cacr.caltech.edu/catalina/AllSN.html",
				"alias":"3"
			},
			{
				"name":"Gaia Photometric Science Alerts",
				"url":"http://gsaweb.ast.cam.ac.uk/alerts/alertsindex",
				"alias":"4"
			},
			{
				"name":"Transient Name Server",
				"url":"https://wis-tns.weizmann.ac.il/",
				"alias":"5"
			},
			{
				"name":"Latest Supernovae",
				"secondary":true,
				"url":"http://www.rochesterastronomy.org/snimages/snredshiftall.html",
				"alias":"6"
			},
			{
				"name":"The Open Supernova Catalog",
				"bibcode":"2017ApJ...835...64G",
				"reference":"Guillochon et al. (2017)",
				"secondary":true,
				"url":"https://sne.space",
				"alias":"7"
			}
		],
		"alias":[
			{
				"value":"CSS170516:121702+400911",
				"source":"3,6"
			},
			{
				"value":"AT2017egf",
				"source":"2,3,4,5,6"
			},
			{
				"value":"ATLAS17fqm",
				"source":"3,6"
			},
			{
				"value":"Gaia17bkb",
				"source":"3,6"
			},
			{
				"value":"MLS170602:121702+400911",
				"source":"2,3,6"
			}
		],
		"claimedtype":[
			{
				"value":"Candidate",
				"source":"4"
			}
		],
		"dec":[
			{
				"value":"+40:09:10.62",
				"u_value":"degrees",
				"source":"3,6"
			},
			{
				"value":"+40:09:10.8",
				"u_value":"degrees",
				"source":"4"
			},
			{
				"value":"+40:09:10.44",
				"u_value":"degrees",
				"source":"2"
			}
		],
		"discoverdate":[
			{
				"value":"2017/05/16",
				"source":"3,6"
			}
		],
		"discoverer":[
			{
				"value":"CRTS",
				"source":"3,6"
			}
		],
		"ebv":[
			{
				"value":"0.0186",
				"derived":true,
				"e_value":"0.0005",
				"source":"1,7"
			}
		],
		"maxappmag":[
			{
				"value":"18.34",
				"derived":true,
				"source":"4,7"
			}
		],
		"maxband":[
			{
				"value":"G",
				"derived":true,
				"source":"4,7"
			}
		],
		"maxdate":[
			{
				"value":"2017/05/28",
				"derived":true,
				"source":"4,7"
			}
		],
		"maxvisualappmag":[
			{
				"value":"18.34",
				"derived":true,
				"source":"4,7"
			}
		],
		"maxvisualband":[
			{
				"value":"G",
				"derived":true,
				"source":"4,7"
			}
		],
		"maxvisualdate":[
			{
				"value":"2017/05/28",
				"derived":true,
				"source":"4,7"
			}
		],
		"ra":[
			{
				"value":"12:17:01.845",
				"u_value":"hours",
				"source":"3,6"
			},
			{
				"value":"12:17:01.92",
				"u_value":"hours",
				"source":"2,4"
			}
		],
		"photometry":[
			{
				"band":"C",
				"e_magnitude":"1.0",
				"host":true,
				"magnitude":"15.7",
				"telescope":"Catalina Schmidt",
				"source":"2"
			},
			{
				"time":"54536.27440568",
				"band":"C",
				"e_magnitude":"0.542061363551",
				"e_time":"0.125",
				"includeshost":true,
				"magnitude":"21.2639",
				"telescope":"Catalina Schmidt",
				"u_time":"MJD",
				"source":"2"
			},
			{
				"time":"54806.41914244",
				"band":"C",
				"e_magnitude":"0.464560248453",
				"e_time":"0.125",
				"includeshost":true,
				"magnitude":"21.0031",
				"telescope":"Catalina Schmidt",
				"u_time":"MJD",
				"source":"2"
			},
			{
				"time":"55650.31351722",
				"band":"C",
				"e_magnitude":"0.61916316354",
				"e_time":"0.125",
				"includeshost":true,
				"magnitude":"21.4046",
				"telescope":"Catalina Schmidt",
				"u_time":"MJD",
				"source":"2"
			},
			{
				"time":"57808.5",
				"band":"C",
				"e_magnitude":"0.267895131588",
				"e_time":"0.125",
				"includeshost":true,
				"magnitude":"21.8606",
				"telescope":"Catalina Schmidt",
				"u_time":"MJD",
				"source":"2"
			},
			{
				"time":"57861.1909954",
				"band":"G",
				"instrument":"Astrometric",
				"magnitude":"21.5",
				"observer":"Robot",
				"telescope":"Gaia",
				"u_time":"MJD",
				"upperlimit":true,
				"source":"5"
			},
			{
				"time":"57870.4809954",
				"band":"cyan",
				"instrument":"ACAM1",
				"magnitude":"19.48",
				"observer":"Robot",
				"telescope":"ATLAS1",
				"u_time":"MJD",
				"upperlimit":true,
				"source":"5"
			},
			{
				"time":"57891.315",
				"band":"orange",
				"e_magnitude":"0.14",
				"instrument":"ACAM1",
				"magnitude":"18.86",
				"observer":"Robot",
				"telescope":"ATLAS1",
				"u_time":"MJD",
				"source":"5"
			},
			{
				"time":"57901.6489931",
				"band":"G",
				"e_magnitude":"0.2",
				"instrument":"Astrometric",
				"magnitude":"18.44",
				"observer":"Robot",
				"telescope":"Gaia",
				"u_time":"MJD",
				"source":"5"
			},
			{
				"time":"57901.650",
				"band":"G",
				"e_magnitude":"0.0",
				"instrument":"Astrometric",
				"magnitude":"18.34",
				"telescope":"GAIA",
				"u_time":"MJD",
				"source":"4"
			},
			{
				"time":"57901.724",
				"band":"G",
				"e_magnitude":"0.0",
				"instrument":"Astrometric",
				"magnitude":"18.34",
				"telescope":"GAIA",
				"u_time":"MJD",
				"source":"4"
			},
			{
				"time":"57906.5",
				"band":"C",
				"e_magnitude":"0.0745437238699",
				"e_time":"0.125",
				"includeshost":true,
				"magnitude":"18.4099",
				"telescope":"Catalina Schmidt",
				"u_time":"MJD",
				"source":"2"
			},
			{
				"time":"57906.5",
				"band":"C",
				"e_magnitude":"0.0756778719581",
				"e_time":"0.125",
				"includeshost":true,
				"magnitude":"18.4805",
				"telescope":"Catalina Schmidt",
				"u_time":"MJD",
				"source":"2"
			},
			{
				"time":"57906.5",
				"band":"C",
				"e_magnitude":"0.075894179925",
				"e_time":"0.125",
				"includeshost":true,
				"magnitude":"18.4986",
				"telescope":"Catalina Schmidt",
				"u_time":"MJD",
				"source":"2"
			},
			{
				"time":"57906.5",
				"band":"C",
				"e_magnitude":"0.0773789350681",
				"e_time":"0.125",
				"includeshost":true,
				"magnitude":"18.5785",
				"telescope":"Catalina Schmidt",
				"u_time":"MJD",
				"source":"2"
			},
			{
				"time":"57934.208",
				"band":"G",
				"e_magnitude":"0.0",
				"instrument":"Astrometric",
				"magnitude":"19.67",
				"telescope":"GAIA",
				"u_time":"MJD",
				"source":"4"
			},
			{
				"time":"58126.5",
				"band":"C",
				"e_magnitude":"0.285045504804",
				"e_time":"0.125",
				"includeshost":true,
				"magnitude":"22.0652",
				"telescope":"Catalina Schmidt",
				"u_time":"MJD",
				"source":"2"
			},
			{
				"time":"58143.5",
				"band":"C",
				"e_magnitude":"0.266213033697",
				"e_time":"0.125",
				"includeshost":true,
				"magnitude":"22.0414",
				"telescope":"Catalina Schmidt",
				"u_time":"MJD",
				"source":"2"
			},
			{
				"time":"58186.5",
				"band":"C",
				"e_magnitude":"0.199151379238",
				"e_time":"0.125",
				"includeshost":true,
				"magnitude":"21.4719",
				"telescope":"Catalina Schmidt",
				"u_time":"MJD",
				"source":"2"
			},
			{
				"time":"58293.5",
				"band":"C",
				"e_magnitude":"0.195611252933",
				"e_time":"0.125",
				"includeshost":true,
				"magnitude":"21.0598",
				"telescope":"Catalina Schmidt",
				"u_time":"MJD",
				"source":"2"
			},
			{
				"time":"58546.5",
				"band":"C",
				"e_magnitude":"0.381589370708",
				"e_time":"0.125",
				"includeshost":true,
				"magnitude":"22.5513",
				"telescope":"Catalina Schmidt",
				"u_time":"MJD",
				"source":"2"
			},
			{
				"time":"58570.5",
				"band":"C",
				"e_magnitude":"0.192902767269",
				"e_time":"0.125",
				"includeshost":true,
				"magnitude":"21.2677",
				"telescope":"Catalina Schmidt",
				"u_time":"MJD",
				"source":"2"
			},
			{
				"time":"58643.5",
				"band":"C",
				"e_magnitude":"0.296557199623",
				"e_time":"0.125",
				"includeshost":true,
				"magnitude":"22.0876",
				"telescope":"Catalina Schmidt",
				"u_time":"MJD",
				"source":"2"
			}
		]
	}
}