{
	"OGLE15xq":{
		"name":"OGLE15xq",
		"aliases":[
			"OGLE15xq"
		],
		"sources":[
			{
				"name":"OGLE page",
				"url":"http://ogle.astrouw.edu.pl/ogle4/transients/transients.html",
				"alias":"1"
			},
			{
				"name":"Latest Supernovae",
				"url":"http://www.rochesterastronomy.org/snimages/snredshiftall.html",
				"alias":"2",
				"secondary":true
			},
			{
				"name":"OGLE-IV Transient Detection System",
				"url":"http://ogle.astrouw.edu.pl/ogle4/transients/transients.html",
				"alias":"3"
			}
		],
		"claimedtype":[
			{
				"value":"Candidate",
				"source":"3"
			}
		],
		"discoverday":"14",
		"discoverer":"OGLE-IV wide field survey",
		"discovermonth":"12",
		"discoveryear":"2015",
		"maxappmag":"19.9",
		"maxday":"14",
		"maxmonth":"12",
		"maxyear":"2015",
		"sndec":[
			{
				"value":"-70:33:43.9",
				"source":"1,2,3"
			}
		],
		"snra":[
			{
				"value":"23:31:33.99",
				"source":"1,2,3"
			}
		],
		"photometry":[
			{
				"timeunit":"MJD",
				"time":"56870.31060",
				"band":"I",
				"abmag":"22",
				"source":"3",
				"upperlimit":true
			},
			{
				"timeunit":"MJD",
				"time":"56876.34627",
				"band":"I",
				"abmag":"22",
				"source":"3",
				"upperlimit":true
			},
			{
				"timeunit":"MJD",
				"time":"56881.26509",
				"band":"I",
				"abmag":"22",
				"source":"3",
				"upperlimit":true
			},
			{
				"timeunit":"MJD",
				"time":"56885.27937",
				"band":"I",
				"abmag":"22",
				"source":"3",
				"upperlimit":true
			},
			{
				"timeunit":"MJD",
				"time":"56889.25106",
				"band":"I",
				"abmag":"22",
				"source":"3",
				"upperlimit":true
			},
			{
				"timeunit":"MJD",
				"time":"56895.25150",
				"band":"I",
				"abmag":"22",
				"source":"3",
				"upperlimit":true
			},
			{
				"timeunit":"MJD",
				"time":"56904.12583",
				"band":"I",
				"abmag":"22",
				"source":"3",
				"upperlimit":true
			},
			{
				"timeunit":"MJD",
				"time":"56910.19600",
				"band":"I",
				"abmag":"22",
				"source":"3",
				"upperlimit":true
			},
			{
				"timeunit":"MJD",
				"time":"56918.17452",
				"band":"I",
				"abmag":"22",
				"source":"3",
				"upperlimit":true
			},
			{
				"timeunit":"MJD",
				"time":"56922.17645",
				"band":"I",
				"abmag":"22",
				"source":"3",
				"upperlimit":true
			},
			{
				"timeunit":"MJD",
				"time":"56927.17951",
				"band":"I",
				"abmag":"22",
				"source":"3",
				"upperlimit":true
			},
			{
				"timeunit":"MJD",
				"time":"56931.12588",
				"band":"I",
				"abmag":"22",
				"source":"3",
				"upperlimit":true
			},
			{
				"timeunit":"MJD",
				"time":"56938.10812",
				"band":"I",
				"abmag":"21.966",
				"aberr":"0.648",
				"source":"3"
			},
			{
				"timeunit":"MJD",
				"time":"56941.07278",
				"band":"I",
				"abmag":"22",
				"source":"3",
				"upperlimit":true
			},
			{
				"timeunit":"MJD",
				"time":"56948.05883",
				"band":"I",
				"abmag":"22",
				"source":"3",
				"upperlimit":true
			},
			{
				"timeunit":"MJD",
				"time":"56951.08661",
				"band":"I",
				"abmag":"22",
				"source":"3",
				"upperlimit":true
			},
			{
				"timeunit":"MJD",
				"time":"56954.06945",
				"band":"I",
				"abmag":"22",
				"source":"3",
				"upperlimit":true
			},
			{
				"timeunit":"MJD",
				"time":"56957.09234",
				"band":"I",
				"abmag":"22",
				"source":"3",
				"upperlimit":true
			},
			{
				"timeunit":"MJD",
				"time":"56958.07531",
				"band":"I",
				"abmag":"22",
				"source":"3",
				"upperlimit":true
			},
			{
				"timeunit":"MJD",
				"time":"56962.19060",
				"band":"I",
				"abmag":"22",
				"source":"3",
				"upperlimit":true
			},
			{
				"timeunit":"MJD",
				"time":"56967.01673",
				"band":"I",
				"abmag":"22",
				"source":"3",
				"upperlimit":true
			},
			{
				"timeunit":"MJD",
				"time":"56971.05194",
				"band":"I",
				"abmag":"21.821",
				"aberr":"0.450",
				"source":"3"
			},
			{
				"timeunit":"MJD",
				"time":"56975.02689",
				"band":"I",
				"abmag":"22",
				"source":"3",
				"upperlimit":true
			},
			{
				"timeunit":"MJD",
				"time":"56980.02239",
				"band":"I",
				"abmag":"22",
				"source":"3",
				"upperlimit":true
			},
			{
				"timeunit":"MJD",
				"time":"56984.02482",
				"band":"I",
				"abmag":"22",
				"source":"3",
				"upperlimit":true
			},
			{
				"timeunit":"MJD",
				"time":"56988.07495",
				"band":"I",
				"abmag":"22",
				"source":"3",
				"upperlimit":true
			},
			{
				"timeunit":"MJD",
				"time":"56993.03192",
				"band":"I",
				"abmag":"22",
				"source":"3",
				"upperlimit":true
			},
			{
				"timeunit":"MJD",
				"time":"56997.03192",
				"band":"I",
				"abmag":"22",
				"source":"3",
				"upperlimit":true
			},
			{
				"timeunit":"MJD",
				"time":"57000.06369",
				"band":"I",
				"abmag":"22",
				"source":"3",
				"upperlimit":true
			},
			{
				"timeunit":"MJD",
				"time":"57005.07006",
				"band":"I",
				"abmag":"22",
				"source":"3",
				"upperlimit":true
			},
			{
				"timeunit":"MJD",
				"time":"57010.03931",
				"band":"I",
				"abmag":"22",
				"source":"3",
				"upperlimit":true
			},
			{
				"timeunit":"MJD",
				"time":"57016.05701",
				"band":"I",
				"abmag":"22",
				"source":"3",
				"upperlimit":true
			},
			{
				"timeunit":"MJD",
				"time":"57021.05488",
				"band":"I",
				"abmag":"22",
				"source":"3",
				"upperlimit":true
			},
			{
				"timeunit":"MJD",
				"time":"57196.42954",
				"band":"I",
				"abmag":"22",
				"source":"3",
				"upperlimit":true
			},
			{
				"timeunit":"MJD",
				"time":"57204.29428",
				"band":"I",
				"abmag":"22",
				"source":"3",
				"upperlimit":true
			},
			{
				"timeunit":"MJD",
				"time":"57206.37551",
				"band":"I",
				"abmag":"22",
				"source":"3",
				"upperlimit":true
			},
			{
				"timeunit":"MJD",
				"time":"57212.36830",
				"band":"I",
				"abmag":"22",
				"source":"3",
				"upperlimit":true
			},
			{
				"timeunit":"MJD",
				"time":"57220.35712",
				"band":"I",
				"abmag":"22",
				"source":"3",
				"upperlimit":true
			},
			{
				"timeunit":"MJD",
				"time":"57226.34345",
				"band":"I",
				"abmag":"22",
				"source":"3",
				"upperlimit":true
			},
			{
				"timeunit":"MJD",
				"time":"57230.25932",
				"band":"I",
				"abmag":"22",
				"source":"3",
				"upperlimit":true
			},
			{
				"timeunit":"MJD",
				"time":"57236.32977",
				"band":"I",
				"abmag":"22",
				"source":"3",
				"upperlimit":true
			},
			{
				"timeunit":"MJD",
				"time":"57253.24109",
				"band":"I",
				"abmag":"22",
				"source":"3",
				"upperlimit":true
			},
			{
				"timeunit":"MJD",
				"time":"57256.22013",
				"band":"I",
				"abmag":"22",
				"source":"3",
				"upperlimit":true
			},
			{
				"timeunit":"MJD",
				"time":"57261.23629",
				"band":"I",
				"abmag":"22",
				"source":"3",
				"upperlimit":true
			},
			{
				"timeunit":"MJD",
				"time":"57264.24721",
				"band":"I",
				"abmag":"22",
				"source":"3",
				"upperlimit":true
			},
			{
				"timeunit":"MJD",
				"time":"57267.23595",
				"band":"I",
				"abmag":"22",
				"source":"3",
				"upperlimit":true
			},
			{
				"timeunit":"MJD",
				"time":"57270.21970",
				"band":"I",
				"abmag":"22",
				"source":"3",
				"upperlimit":true
			},
			{
				"timeunit":"MJD",
				"time":"57286.13317",
				"band":"I",
				"abmag":"22",
				"source":"3",
				"upperlimit":true
			},
			{
				"timeunit":"MJD",
				"time":"57287.10935",
				"band":"I",
				"abmag":"22",
				"source":"3",
				"upperlimit":true
			},
			{
				"timeunit":"MJD",
				"time":"57294.12383",
				"band":"I",
				"abmag":"22",
				"source":"3",
				"upperlimit":true
			},
			{
				"timeunit":"MJD",
				"time":"57299.10254",
				"band":"I",
				"abmag":"22",
				"source":"3",
				"upperlimit":true
			},
			{
				"timeunit":"MJD",
				"time":"57306.11638",
				"band":"I",
				"abmag":"22",
				"source":"3",
				"upperlimit":true
			},
			{
				"timeunit":"MJD",
				"time":"57312.08245",
				"band":"I",
				"abmag":"22",
				"source":"3",
				"upperlimit":true
			},
			{
				"timeunit":"MJD",
				"time":"57317.06834",
				"band":"I",
				"abmag":"22",
				"source":"3",
				"upperlimit":true
			},
			{
				"timeunit":"MJD",
				"time":"57321.08089",
				"band":"I",
				"abmag":"22",
				"source":"3",
				"upperlimit":true
			},
			{
				"timeunit":"MJD",
				"time":"57327.12125",
				"band":"I",
				"abmag":"22",
				"source":"3",
				"upperlimit":true
			},
			{
				"timeunit":"MJD",
				"time":"57337.06468",
				"band":"I",
				"abmag":"22",
				"source":"3",
				"upperlimit":true
			},
			{
				"timeunit":"MJD",
				"time":"57342.02025",
				"band":"I",
				"abmag":"22",
				"source":"3",
				"upperlimit":true
			},
			{
				"timeunit":"MJD",
				"time":"57345.01720",
				"band":"I",
				"abmag":"22",
				"source":"3",
				"upperlimit":true
			},
			{
				"timeunit":"MJD",
				"time":"57348.03058",
				"band":"I",
				"abmag":"22",
				"source":"3",
				"upperlimit":true
			},
			{
				"timeunit":"MJD",
				"time":"57354.04353",
				"band":"I",
				"abmag":"22",
				"source":"3",
				"upperlimit":true
			},
			{
				"timeunit":"MJD",
				"time":"57356.07172",
				"band":"I",
				"abmag":"22",
				"source":"3",
				"upperlimit":true
			},
			{
				"timeunit":"MJD",
				"time":"57360.02588",
				"band":"I",
				"abmag":"22",
				"source":"3",
				"upperlimit":true
			},
			{
				"timeunit":"MJD",
				"time":"57364.03087",
				"band":"I",
				"abmag":"21.676",
				"aberr":"0.489",
				"source":"3"
			},
			{
				"timeunit":"MJD",
				"time":"57370.5",
				"band":"",
				"abmag":"19.9",
				"source":"1,2"
			},
			{
				"timeunit":"MJD",
				"time":"57374.03285",
				"band":"I",
				"abmag":"19.661",
				"aberr":"0.093",
				"source":"3"
			},
			{
				"timeunit":"MJD",
				"time":"57377.03667",
				"band":"I",
				"abmag":"19.654",
				"aberr":"0.077",
				"source":"3"
			},
			{
				"timeunit":"MJD",
				"time":"57381.03927",
				"band":"I",
				"abmag":"19.648",
				"aberr":"0.074",
				"source":"3"
			},
			{
				"timeunit":"MJD",
				"time":"57386.03914",
				"band":"I",
				"abmag":"20.082",
				"aberr":"0.103",
				"source":"3"
			}
		]
	}
}