{
	"PS18cr":{
		"schema":"https://github.com/astrocatalogs/supernovae/blob/d3ef5fc/SCHEMA.md",
		"name":"PS18cr",
		"sources":[
			{
				"name":"2011ApJ...737..103S",
				"bibcode":"2011ApJ...737..103S",
				"reference":"Schlafly & Finkbeiner (2011)",
				"alias":"1"
			},
			{
				"name":"Transient Name Server",
				"url":"https://wis-tns.weizmann.ac.il/",
				"alias":"2"
			},
			{
				"name":"Pan-STARRS 3Pi",
				"url":"https://wis-tns.weizmann.ac.il/object/2018dn",
				"alias":"3"
			},
			{
				"name":"Latest Supernovae",
				"secondary":true,
				"url":"http://www.rochesterastronomy.org/snimages/snredshiftall.html",
				"alias":"4"
			},
			{
				"name":"The Open Supernova Catalog",
				"bibcode":"2017ApJ...835...64G",
				"reference":"Guillochon et al. (2017)",
				"secondary":true,
				"url":"https://sne.space",
				"alias":"5"
			}
		],
		"alias":[
			{
				"value":"PS18cr",
				"source":"2,3,4"
			},
			{
				"value":"AT2018dn",
				"source":"2,3,4"
			}
		],
		"dec":[
			{
				"value":"+63:22:16.99",
				"u_value":"degrees",
				"source":"2,3,4"
			},
			{
				"value":"+63:22:16.8",
				"u_value":"degrees",
				"source":"3"
			}
		],
		"discoverdate":[
			{
				"value":"2018/01/06.583993",
				"source":"2"
			}
		],
		"discoverer":[
			{
				"value":"Pan-STARRS1",
				"source":"2"
			},
			{
				"value":"PS1",
				"source":"3,4"
			}
		],
		"ebv":[
			{
				"value":"0.0098",
				"derived":true,
				"e_value":"0.0006",
				"source":"1,5"
			}
		],
		"host":[
			{
				"value":"2MASX J11230409+6322196",
				"source":"3"
			}
		],
		"hostdec":[
			{
				"value":"+63:22:19.6",
				"derived":true,
				"u_value":"degrees",
				"source":"5"
			}
		],
		"hostoffsetang":[
			{
				"value":"6.209",
				"derived":true,
				"u_value":"arcseconds",
				"source":"2,3,4,5"
			}
		],
		"hostra":[
			{
				"value":"11:23:04.09",
				"derived":true,
				"u_value":"hours",
				"source":"5"
			}
		],
		"maxappmag":[
			{
				"value":"19.82",
				"derived":true,
				"source":"3,5"
			}
		],
		"maxband":[
			{
				"value":"i",
				"derived":true,
				"source":"3,5"
			}
		],
		"maxdate":[
			{
				"value":"2018/01/06",
				"derived":true,
				"source":"3,5"
			}
		],
		"maxvisualappmag":[
			{
				"value":"19.82",
				"derived":true,
				"source":"3,5"
			}
		],
		"maxvisualband":[
			{
				"value":"i",
				"derived":true,
				"source":"3,5"
			}
		],
		"maxvisualdate":[
			{
				"value":"2018/01/06",
				"derived":true,
				"source":"3,5"
			}
		],
		"ra":[
			{
				"value":"11:23:04.928",
				"u_value":"hours",
				"source":"2"
			},
			{
				"value":"11:23:04.930",
				"u_value":"hours",
				"source":"3,4"
			},
			{
				"value":"11:23:04.93",
				"u_value":"hours",
				"source":"3"
			}
		],
		"photometry":[
			{
				"time":"58123.5",
				"magnitude":"19.9",
				"u_time":"MJD",
				"source":"3,4"
			},
			{
				"time":"58124.5835733624",
				"band":"i",
				"e_magnitude":"0.211685",
				"instrument":"GPC",
				"magnitude":"19.8718",
				"telescope":"Pan-STARRS1",
				"u_time":"MJD",
				"source":"3"
			},
			{
				"time":"58124.5839931",
				"band":"i",
				"e_magnitude":"0.21",
				"instrument":"GPC1",
				"magnitude":"19.87",
				"observer":"Robot",
				"telescope":"PS1",
				"u_time":"MJD",
				"source":"2"
			},
			{
				"time":"58124.5972288045",
				"band":"i",
				"e_magnitude":"0.220149",
				"instrument":"GPC",
				"magnitude":"19.9186",
				"telescope":"Pan-STARRS1",
				"u_time":"MJD",
				"source":"3"
			},
			{
				"time":"58124.6108264523",
				"band":"i",
				"e_magnitude":"0.173969",
				"instrument":"GPC",
				"magnitude":"19.8162",
				"telescope":"Pan-STARRS1",
				"u_time":"MJD",
				"source":"3"
			},
			{
				"time":"58124.6244306737",
				"band":"i",
				"e_magnitude":"0.172112",
				"instrument":"GPC",
				"magnitude":"19.8824",
				"telescope":"Pan-STARRS1",
				"u_time":"MJD",
				"source":"3"
			}
		]
	}
}